voiceobs/__init__.py
voiceobs/_version.py
voiceobs/analyzer.py
voiceobs/classifier.py
voiceobs/cli.py
voiceobs/compare.py
voiceobs/config.py
voiceobs/context.py
voiceobs/decorators.py
voiceobs/exporters.py
voiceobs/failures.py
voiceobs/py.typed
voiceobs/report.py
voiceobs/stages.py
voiceobs/timeline.py
voiceobs/tracing.py
voiceobs/types.py
voiceobs/eval/__init__.py
voiceobs/eval/evaluator.py
voiceobs/eval/types.py
voiceobs/eval/providers/__init__.py
voiceobs/eval/providers/anthropic.py
voiceobs/eval/providers/base.py
voiceobs/eval/providers/gemini.py
voiceobs/eval/providers/openai.py
voiceobs/eval/providers/registry.py
voiceobs/integrations/__init__.py
voiceobs/integrations/base.py
voiceobs/integrations/livekit.py
voiceobs/integrations/vocode.py
voiceobs-0.0.2.dist-info/METADATA
voiceobs-0.0.2.dist-info/WHEEL
voiceobs-0.0.2.dist-info/entry_points.txt
voiceobs-0.0.2.dist-info/licenses/LICENSE
voiceobs-0.0.2.dist-info/RECORD
