Metadata-Version: 2.4
Name: voiceobs
Version: 0.0.2
Summary: Open, vendor-neutral observability for voice AI conversations using OpenTelemetry
Project-URL: Homepage, https://github.com/voice-observation/voiceobs
Project-URL: Documentation, https://github.com/voice-observation/voiceobs#readme
Project-URL: Repository, https://github.com/voice-observation/voiceobs
Project-URL: Issues, https://github.com/voice-observation/voiceobs/issues
Author: voiceobs contributors
License-Expression: Apache-2.0
License-File: LICENSE
Keywords: ai,observability,opentelemetry,tracing,voice
Classifier: Development Status :: 3 - Alpha
Classifier: Intended Audience :: Developers
Classifier: License :: OSI Approved :: Apache Software License
Classifier: Programming Language :: Python :: 3
Classifier: Programming Language :: Python :: 3.9
Classifier: Programming Language :: Python :: 3.10
Classifier: Programming Language :: Python :: 3.11
Classifier: Programming Language :: Python :: 3.12
Classifier: Topic :: Software Development :: Libraries :: Python Modules
Classifier: Topic :: System :: Monitoring
Requires-Python: >=3.9
Requires-Dist: opentelemetry-api>=1.20.0
Requires-Dist: opentelemetry-sdk>=1.20.0
Requires-Dist: pyyaml>=6.0.0
Requires-Dist: typer>=0.9.0
Provides-Extra: dev
Requires-Dist: mypy>=1.0.0; extra == 'dev'
Requires-Dist: pydantic>=2.0.0; extra == 'dev'
Requires-Dist: pytest-asyncio>=0.23.0; extra == 'dev'
Requires-Dist: pytest-cov>=4.0.0; extra == 'dev'
Requires-Dist: pytest>=7.0.0; extra == 'dev'
Requires-Dist: ruff>=0.1.0; extra == 'dev'
Provides-Extra: eval
Requires-Dist: langchain-anthropic>=0.3.0; extra == 'eval'
Requires-Dist: langchain-google-genai>=2.0.0; extra == 'eval'
Requires-Dist: langchain-openai>=0.3.0; extra == 'eval'
Requires-Dist: langchain>=0.3.0; extra == 'eval'
